calculadora/__init__.py
calculadora/multiplicacao.py
calculadora/soma.py
calculadora/subtracao.py
calculadora_bootcamp/__init__.py
calculadora_bootcamp/multiplicacao.py
calculadora_bootcamp/soma.py
calculadora_bootcamp/subtracao.py
calculadora_bootcamp-0.0.4.dist-info/METADATA
calculadora_bootcamp-0.0.4.dist-info/WHEEL
calculadora_bootcamp-0.0.4.dist-info/top_level.txt
calculadora_bootcamp-0.0.4.dist-info/RECORD
