Metadata-Version: 2.1
Name: calculadora-bootcamp
Version: 0.0.4
Summary: Criando primeiro package
Home-page: https://github.com/edu-lauer
Author: Eduardo
Author-email: lauer.edu@gmail.com
License: UNKNOWN
Platform: UNKNOWN
Requires-Python: >=3.8
